odoo8_addon_account_due_list_payment_mode-8.0.1.0.0.99.dev23-py2.7-nspkg.pth
odoo8_addon_account_due_list_payment_mode-8.0.1.0.0.99.dev23.dist-info/METADATA
odoo8_addon_account_due_list_payment_mode-8.0.1.0.0.99.dev23.dist-info/RECORD
odoo8_addon_account_due_list_payment_mode-8.0.1.0.0.99.dev23.dist-info/WHEEL
odoo8_addon_account_due_list_payment_mode-8.0.1.0.0.99.dev23.dist-info/namespace_packages.txt
odoo8_addon_account_due_list_payment_mode-8.0.1.0.0.99.dev23.dist-info/top_level.txt
odoo_addons/account_due_list_payment_mode/README.rst
odoo_addons/account_due_list_payment_mode/__init__.py
odoo_addons/account_due_list_payment_mode/__openerp__.py
odoo_addons/account_due_list_payment_mode/i18n/account_due_list_payment_mode.pot
odoo_addons/account_due_list_payment_mode/i18n/ca.po
odoo_addons/account_due_list_payment_mode/i18n/de.po
odoo_addons/account_due_list_payment_mode/i18n/es.po
odoo_addons/account_due_list_payment_mode/i18n/eu.po
odoo_addons/account_due_list_payment_mode/i18n/fi.po
odoo_addons/account_due_list_payment_mode/i18n/fr.po
odoo_addons/account_due_list_payment_mode/i18n/id.po
odoo_addons/account_due_list_payment_mode/i18n/it.po
odoo_addons/account_due_list_payment_mode/i18n/nb.po
odoo_addons/account_due_list_payment_mode/i18n/nl.po
odoo_addons/account_due_list_payment_mode/i18n/pt_BR.po
odoo_addons/account_due_list_payment_mode/i18n/pt_PT.po
odoo_addons/account_due_list_payment_mode/i18n/ro_RO.po
odoo_addons/account_due_list_payment_mode/i18n/sl.po
odoo_addons/account_due_list_payment_mode/i18n/zh_CN.po
odoo_addons/account_due_list_payment_mode/models/__init__.py
odoo_addons/account_due_list_payment_mode/models/account_move_line.py
odoo_addons/account_due_list_payment_mode/static/description/icon.png
odoo_addons/account_due_list_payment_mode/views/payment_view.xml
