Metadata-Version: 2.1
Name: odoo8-addon-account-due-list-payment-mode
Version: 8.0.1.0.0.99.dev23
Summary: Payment due list with payment mode
Home-page: http://www.obertix.net
Author: Odoo Community Association (OCA),Obertix, Free Solutions
Author-email: support@odoo-community.org
License: UNKNOWN
Platform: UNKNOWN
Classifier: Programming Language :: Python
Classifier: Framework :: Odoo
Requires-Python: ~=2.7
Requires-Dist: odoo8-addon-account-due-list
Requires-Dist: odoo8-addon-account-payment-partner
Requires-Dist: odoo (<9.0a,>=8.0a)
